sko/ACA.py
sko/AFSA.py
sko/DE.py
sko/GA.py
sko/IA.py
sko/PSO.py
sko/SA.py
sko/__init__.py
sko/base.py
sko/demo_func.py
sko/tools.py
sko/operators/__init__.py
sko/operators/crossover.py
sko/operators/mutation.py
sko/operators/ranking.py
sko/operators/selection.py
sko/operators_gpu/__init__.py
sko/operators_gpu/crossover_gpu.py
sko/operators_gpu/mutation_gpu.py
sko/operators_gpu/ranking_gpu.py
sko/operators_gpu/selection_gpu.py
sko-0.5.7.dist-info/LICENSE
sko-0.5.7.dist-info/METADATA
sko-0.5.7.dist-info/WHEEL
sko-0.5.7.dist-info/top_level.txt
sko-0.5.7.dist-info/RECORD
