Metadata-Version: 2.1
Name: sko
Version: 0.5.7
Summary: Swarm Intelligence in Python
Home-page: https://github.com/guofei9987/scikit-opt
Author: Guo Fei
Author-email: guofei9987@foxmail.com
License: MIT
Platform: linux
Platform: windows
Platform: macos
Requires-Python: >=3.5
